dibkb_scraper/__init__.py
dibkb_scraper/amazon.py
dibkb_scraper/models.py
dibkb_scraper/playwright.py
dibkb_scraper/utils.py
dibkb_scraper-0.3.4.dist-info/METADATA
dibkb_scraper-0.3.4.dist-info/WHEEL
dibkb_scraper-0.3.4.dist-info/top_level.txt
dibkb_scraper-0.3.4.dist-info/RECORD
