Metadata-Version: 2.4
Name: dibkb_scraper
Version: 0.3.4
Summary: A scraper for Amazon product details and reviews using ASIN
Home-page: https://github.com/dibkb/dibkb_scraper
Author: Dibas K Borborah
Author-email: dibas9110@gmail.com
Classifier: Programming Language :: Python :: 3
Classifier: License :: OSI Approved :: MIT License
Classifier: Operating System :: OS Independent
Requires-Python: >=3.6
Requires-Dist: httpx
Requires-Dist: beautifulsoup4
Requires-Dist: bs4
Requires-Dist: pydantic
Requires-Dist: fake-useragent
Requires-Dist: playwright_stealth
Requires-Dist: pytest-playwright
Dynamic: author
Dynamic: author-email
Dynamic: classifier
Dynamic: description
Dynamic: description-content-type
Dynamic: home-page
Dynamic: requires-dist
Dynamic: requires-python
Dynamic: summary
